quantax/__init__.py
quantax/global_defs.py
quantax/model/__init__.py
quantax/model/backflow.py
quantax/model/conv_nets.py
quantax/model/fermion_mf.py
quantax/model/jastrow.py
quantax/model/shallow_nets.py
quantax/model/transformer.py
quantax/model/triangular_nets.py
quantax/nn/__init__.py
quantax/nn/activation.py
quantax/nn/conv.py
quantax/nn/fermion.py
quantax/nn/initializers.py
quantax/nn/modules.py
quantax/nn/sign.py
quantax/operator/__init__.py
quantax/operator/common_operators.py
quantax/operator/operator.py
quantax/operator/site_operator.py
quantax/optimizer/__init__.py
quantax/optimizer/driver.py
quantax/optimizer/solver.py
quantax/optimizer/sr.py
quantax/optimizer/supervised.py
quantax/optimizer/time_evol.py
quantax/sampler/__init__.py
quantax/sampler/common_samplers.py
quantax/sampler/metropolis.py
quantax/sampler/sampler.py
quantax/sampler/samples.py
quantax/sites/__init__.py
quantax/sites/cluster.py
quantax/sites/common_lattices.py
quantax/sites/lattice.py
quantax/sites/sites.py
quantax/state/__init__.py
quantax/state/fermion_mf.py
quantax/state/lanczos.py
quantax/state/state.py
quantax/state/variational.py
quantax/symmetry/__init__.py
quantax/symmetry/common_symmetries.py
quantax/symmetry/symmetry.py
quantax/symmetry/translation.py
quantax/utils/__init__.py
quantax/utils/array.py
quantax/utils/basis.py
quantax/utils/big_array.py
quantax/utils/data.py
quantax/utils/function.py
quantax/utils/sharding.py
quantax/utils/tree.py
quantax-0.2.1.dist-info/licenses/LICENSE
quantax-0.2.1.dist-info/METADATA
quantax-0.2.1.dist-info/WHEEL
quantax-0.2.1.dist-info/top_level.txt
quantax-0.2.1.dist-info/RECORD
