Metadata-Version: 2.4
Name: quantax
Version: 0.2.1
Summary: Flexible neural quantum states based on JAX
Author: Christopher Roth
Author-email: Ao Chen <chenao.phys@gmail.com>
Requires-Python: <=3.13,>=3.10
License-File: LICENSE
Requires-Dist: numpy>=1.26.0
Requires-Dist: scipy>=1.11.1
Requires-Dist: jax>=0.6.1
Requires-Dist: equinox>=0.11.4
Requires-Dist: lrux>=0.1.0
Provides-Extra: full
Requires-Dist: numpy>=2.0.0; extra == "full"
Requires-Dist: scipy>=1.13.1; extra == "full"
Requires-Dist: matplotlib>=3.8.0; extra == "full"
Requires-Dist: quspin>=1.0.0; extra == "full"
Requires-Dist: jax>=0.6.1; extra == "full"
Requires-Dist: equinox>=0.11.4; extra == "full"
Requires-Dist: lrux>=0.1.0; extra == "full"
Dynamic: license-file
